Metadata-Version: 2.1
Name: outlier-toolkit
Version: 0.1.3
Summary: A Python library for identifying and handling outliers
Home-page: https://github.com/irenebetsy/outlier_library
Author: Irene Betsy D
Author-email: betsydnicholraja@gmail.com
License: Apache License 2.0
Project-URL: Bug Tracker, https://github.com/irenebetsy/outlier_library/issues
Project-URL: Documentation, https://github.com/irenebetsy/outlier_library#readme
Project-URL: Source Code, https://github.com/irenebetsy/outlier_library
Keywords: outlier IQR ZScore Winsorization binning data preprocessing analytics
Classifier: Programming Language :: Python :: 3
Classifier: License :: OSI Approved :: Apache Software License
Classifier: Operating System :: OS Independent
Requires-Python: >=3.7
License-File: LICENSE
